doc_printer/__init__.py
doc_printer/_compat_itertools.py
doc_printer/_compat_singledispatchmethod.py
doc_printer/_compat_singledispatchmethod.pyi
doc_printer/abc.py
doc_printer/doc.py
doc_printer/py.typed
doc_printer/simple.py
doc_printer/smart.py
doc_printer/table.py
doc_printer-0.15.1.dist-info/LICENSE
doc_printer-0.15.1.dist-info/METADATA
doc_printer-0.15.1.dist-info/WHEEL
doc_printer-0.15.1.dist-info/top_level.txt
doc_printer-0.15.1.dist-info/RECORD
