Metadata-Version: 2.1
Name: doc_printer
Version: 0.15.1
Summary: A Wadler-Leijen Pretty Printer in Python.
Author-email: Wen Kokke <wenkokke@users.noreply.github.com>
License: MIT License
Keywords: pretty-printer
Classifier: License :: OSI Approved :: MIT License
Classifier: Topic :: Software Development :: Compilers
Classifier: Programming Language :: Python :: 3 :: Only
Classifier: Programming Language :: Python :: 3
Classifier: Programming Language :: Python :: 3.7
Classifier: Programming Language :: Python :: 3.8
Classifier: Programming Language :: Python :: 3.9
Classifier: Programming Language :: Python :: 3.10
Classifier: Programming Language :: Python :: 3.11
Classifier: Programming Language :: Python :: 3.12
Requires-Python: <3.13,>=3.7.1
License-File: LICENSE
Requires-Dist: dataclasses-json <0.7,>=0.5.7
Requires-Dist: tree-sitter <0.21,>=0.20
Requires-Dist: more-itertools <11,>=9.1.0
Requires-Dist: singledispatchmethod <2,>=1.0 ; python_version < "3.8"
Provides-Extra: docs
Requires-Dist: Sphinx <8,>=5.1.1 ; extra == 'docs'
Requires-Dist: sphinx-bootstrap-theme <0.9,>=0.8.1 ; extra == 'docs'
Provides-Extra: mypy
Requires-Dist: types-setuptools ; extra == 'mypy'
Provides-Extra: test
Requires-Dist: bumpver ; extra == 'test'
Requires-Dist: mypy <2,>=1.1.1 ; extra == 'test'
Requires-Dist: pytest <8,>=7.1.2 ; extra == 'test'
Requires-Dist: pytest-benchmark <5,>=4.0.0 ; extra == 'test'
Requires-Dist: pytest-golden <0.3,>=0.2.2 ; extra == 'test'
